collabnotes/__init__.py
collabnotes/_version.py
collabnotes-0.1.4.data/data/share/jupyter/labextensions/collabnotes/build_log.json
collabnotes-0.1.4.data/data/share/jupyter/labextensions/collabnotes/package.json
collabnotes-0.1.4.data/data/share/jupyter/labextensions/collabnotes/schemas/collabnotes/package.json.orig
collabnotes-0.1.4.data/data/share/jupyter/labextensions/collabnotes/schemas/collabnotes/settings.json
collabnotes-0.1.4.data/data/share/jupyter/labextensions/collabnotes/static/lib_index_js.d4138ac1068df589f97b.js
collabnotes-0.1.4.data/data/share/jupyter/labextensions/collabnotes/static/lib_index_js.d4138ac1068df589f97b.js.map
collabnotes-0.1.4.data/data/share/jupyter/labextensions/collabnotes/static/remoteEntry.eb79a1fbb435d5874a45.js
collabnotes-0.1.4.data/data/share/jupyter/labextensions/collabnotes/static/remoteEntry.eb79a1fbb435d5874a45.js.map
collabnotes-0.1.4.data/data/share/jupyter/labextensions/collabnotes/static/style.js
collabnotes-0.1.4.data/data/share/jupyter/labextensions/collabnotes/static/style_index_js.50806d617bb2ba017efe.js
collabnotes-0.1.4.data/data/share/jupyter/labextensions/collabnotes/static/style_index_js.50806d617bb2ba017efe.js.map
collabnotes-0.1.4.data/data/share/jupyter/labextensions/collabnotes/install.json
collabnotes-0.1.4.dist-info/METADATA
collabnotes-0.1.4.dist-info/WHEEL
collabnotes-0.1.4.dist-info/licenses/LICENSE
collabnotes-0.1.4.dist-info/RECORD
