Metadata-Version: 2.3
Name: collabnotes
Version: 0.1.4
Dynamic: Keywords
Summary: Collaborative note taking
Project-URL: Homepage, https://github.com/dsa-ou/collabnotes
Project-URL: Bug Tracker, https://github.com/dsa-ou/collabnotes/issues
Project-URL: Repository, https://github.com/dsa-ou/collabnotes.git
Author-email: Oli Howson <oli.howson@open.ac.uk>
License: BSD 3-Clause License
License-File: LICENSE
Classifier: Framework :: Jupyter
Classifier: Framework :: Jupyter :: JupyterLab
Classifier: Framework :: Jupyter :: JupyterLab :: 4
Classifier: Framework :: Jupyter :: JupyterLab :: Extensions
Classifier: Framework :: Jupyter :: JupyterLab :: Extensions :: Prebuilt
Classifier: License :: OSI Approved :: BSD License
Classifier: Programming Language :: Python
Classifier: Programming Language :: Python :: 3
Classifier: Programming Language :: Python :: 3.8
Classifier: Programming Language :: Python :: 3.9
Classifier: Programming Language :: Python :: 3.10
Classifier: Programming Language :: Python :: 3.11
Classifier: Programming Language :: Python :: 3.12
Requires-Python: >=3.8
